azhacks/__init__.py
azhacks/container_manager.py
azhacks/py.typed
azhacks/queue_manager.py
azhacks/storage_resource_manager.py
azhacks/table_manager.py
azhacks-0.1.6.dist-info/METADATA
azhacks-0.1.6.dist-info/WHEEL
azhacks-0.1.6.dist-info/licenses/LICENSE
azhacks-0.1.6.dist-info/RECORD
