Metadata-Version: 2.3
Name: azhacks
Version: 0.1.6
Summary: Add your description here
Requires-Python: >=3.12
Requires-Dist: asyncer>=0.0.8
Requires-Dist: azure-data-tables>=12.6.0
Requires-Dist: azure-storage-blob>=12.24.0
Requires-Dist: azure-storage-queue>=12.12.0
